virtualship/__init__.py
virtualship/_version_setup.py
virtualship/errors.py
virtualship/utils.py
virtualship/cli/__init__.py
virtualship/cli/_plan.py
virtualship/cli/_run.py
virtualship/cli/commands.py
virtualship/cli/main.py
virtualship/cli/validator_utils.py
virtualship/expedition/__init__.py
virtualship/expedition/simulate_schedule.py
virtualship/instruments/__init__.py
virtualship/instruments/adcp.py
virtualship/instruments/argo_float.py
virtualship/instruments/base.py
virtualship/instruments/ctd.py
virtualship/instruments/ctd_bgc.py
virtualship/instruments/drifter.py
virtualship/instruments/ship_underwater_st.py
virtualship/instruments/types.py
virtualship/instruments/xbt.py
virtualship/make_realistic/__init__.py
virtualship/make_realistic/adcp_make_realistic.py
virtualship/make_realistic/ctd_make_realistic.py
virtualship/models/__init__.py
virtualship/models/checkpoint.py
virtualship/models/expedition.py
virtualship/models/location.py
virtualship/models/spacetime.py
virtualship/static/__init__.py
virtualship/static/expedition.yaml
virtualship-0.3.2.dist-info/licenses/LICENSE
virtualship-0.3.2.dist-info/METADATA
virtualship-0.3.2.dist-info/WHEEL
virtualship-0.3.2.dist-info/entry_points.txt
virtualship-0.3.2.dist-info/top_level.txt
virtualship-0.3.2.dist-info/RECORD
