Metadata-Version: 2.4
Name: virtualship
Version: 0.3.2
Summary: Code for the Virtual Ship Classroom, where Marine Scientists can combine Copernicus Marine Data with an OceanParcels ship to go on a virtual expedition.
Author: oceanparcels.org team
License: MIT License
Project-URL: Homepage, https://oceanparcels.org/
Project-URL: Repository, https://github.com/OceanParcels/virtualship
Project-URL: Documentation, https://virtualship.readthedocs.io/
Project-URL: Bug Tracker, https://github.com/OceanParcels/virtualship/issues
Project-URL: Changelog, https://github.com/OceanParcels/virtualship/releases
Classifier: Development Status :: 3 - Alpha
Classifier: License :: OSI Approved :: MIT License
Classifier: Programming Language :: Python
Classifier: Programming Language :: Python :: 3
Classifier: Programming Language :: Python :: 3 :: Only
Classifier: Programming Language :: Python :: 3.10
Classifier: Programming Language :: Python :: 3.11
Classifier: Programming Language :: Python :: 3.12
Classifier: Operating System :: OS Independent
Classifier: Topic :: Scientific/Engineering
Classifier: Topic :: Education
Classifier: Intended Audience :: Education
Requires-Python: >=3.10
License-File: LICENSE
Requires-Dist: click
Requires-Dist: parcels>3.1.0
Requires-Dist: pyproj<4,>=3
Requires-Dist: sortedcontainers==2.4.0
Requires-Dist: opensimplex==0.4.5
Requires-Dist: numpy<2,>=1
Requires-Dist: pydantic<3,>=2
Requires-Dist: PyYAML
Requires-Dist: copernicusmarine>=2.2.2
Requires-Dist: yaspin
Requires-Dist: textual
Requires-Dist: openpyxl
Dynamic: license-file
